[{"word":"beefy","phonetic":"/ˈbiːfi/","phonetics":[{"text":"/ˈbiːfi/","audio":""}],"meanings":[{"partOfSpeech":"adjective","definitions":[{"definition":"Similar to, or tasting like beef.","synonyms":[],"antonyms":[]},{"definition":"Containing beef.","synonyms":[],"antonyms":[]},{"definition":"Strong or muscular.","synonyms":[],"antonyms":[],"example":"The barman was a big, beefy guy with his sleeves rolled up and tattoos on his arms."},{"definition":"Sturdy; robust.","synonyms":[],"antonyms":[],"example":"The software slows down even a beefy computer."}],"synonyms":[],"antonyms":[]}],"license":{"name":"CC BY-SA 3.0","url":"https://creativecommons.org/licenses/by-sa/3.0"},"sourceUrls":["https://en.wiktionary.org/wiki/beefy"]}]