[{"word":"frass","phonetics":[],"meanings":[{"partOfSpeech":"noun","definitions":[{"definition":"The droppings or excrement of insects.","synonyms":[],"antonyms":[]}],"synonyms":[],"antonyms":[]}],"license":{"name":"CC BY-SA 3.0","url":"https://creativecommons.org/licenses/by-sa/3.0"},"sourceUrls":["https://en.wiktionary.org/wiki/frass"]},{"word":"frass","phonetics":[],"meanings":[{"partOfSpeech":"adjective","definitions":[{"definition":"Under the influence of marijuana, stoned","synonyms":[],"antonyms":[]}],"synonyms":[],"antonyms":[]}],"license":{"name":"CC BY-SA 3.0","url":"https://creativecommons.org/licenses/by-sa/3.0"},"sourceUrls":["https://en.wiktionary.org/wiki/frass"]}]