[{"word":"harry","phonetic":"/hæɹi/","phonetics":[{"text":"/hæɹi/","audio":""},{"text":"/hæɹi/","audio":""}],"meanings":[{"partOfSpeech":"verb","definitions":[{"definition":"To plunder, pillage, assault.","synonyms":[],"antonyms":[]},{"definition":"To make repeated attacks on an enemy.","synonyms":[],"antonyms":[]},{"definition":"To strip, lay waste, ravage.","synonyms":[],"antonyms":[]},{"definition":"To harass, bother or distress with demands, threats, or criticism.","synonyms":[],"antonyms":[]}],"synonyms":[],"antonyms":[]}],"license":{"name":"CC BY-SA 3.0","url":"https://creativecommons.org/licenses/by-sa/3.0"},"sourceUrls":["https://en.wiktionary.org/wiki/harry"]}]