[{"word":"koans","phonetics":[],"meanings":[{"partOfSpeech":"noun","definitions":[{"definition":"A story about a Zen master and his student, sometimes like a riddle, other times like a fable, which has become an object of Zen study, and which, when meditated upon, may unlock mechanisms in the Zen student’s mind leading to satori.","synonyms":[],"antonyms":[]},{"definition":"A riddle with no solution, used to provoke reflection on the inadequacy of logical reasoning, and to lead to enlightenment.","synonyms":[],"antonyms":[]}],"synonyms":[],"antonyms":[]}],"license":{"name":"CC BY-SA 3.0","url":"https://creativecommons.org/licenses/by-sa/3.0"},"sourceUrls":["https://en.wiktionary.org/wiki/koan","https://en.wiktionary.org/wiki/koans"]}]