[{"word":"morph","phonetic":"/mɔː(ɹ)f/","phonetics":[{"text":"/mɔː(ɹ)f/","audio":"https://api.dictionaryapi.dev/media/pronunciations/en/morph-uk.mp3","sourceUrl":"https://commons.wikimedia.org/w/index.php?curid=88681167","license":{"name":"BY-SA 4.0","url":"https://creativecommons.org/licenses/by-sa/4.0"}}],"meanings":[{"partOfSpeech":"noun","definitions":[{"definition":"(grammar) A physical form representing some morpheme in language. It is a recurrent distinctive sound or sequence of sounds.","synonyms":[],"antonyms":[]},{"definition":"An allomorph: one of a set of realizations that a morpheme can have in different contexts.","synonyms":[],"antonyms":[]}],"synonyms":[],"antonyms":[]}],"license":{"name":"CC BY-SA 3.0","url":"https://creativecommons.org/licenses/by-sa/3.0"},"sourceUrls":["https://en.wiktionary.org/wiki/morph"]},{"word":"morph","phonetic":"/mɔː(ɹ)f/","phonetics":[{"text":"/mɔː(ɹ)f/","audio":"https://api.dictionaryapi.dev/media/pronunciations/en/morph-uk.mp3","sourceUrl":"https://commons.wikimedia.org/w/index.php?curid=88681167","license":{"name":"BY-SA 4.0","url":"https://creativecommons.org/licenses/by-sa/4.0"}}],"meanings":[{"partOfSpeech":"noun","definitions":[{"definition":"Local variety of a species, distinguishable from other populations of the species by morphology or behaviour.","synonyms":[],"antonyms":[]}],"synonyms":[],"antonyms":[]}],"license":{"name":"CC BY-SA 3.0","url":"https://creativecommons.org/licenses/by-sa/3.0"},"sourceUrls":["https://en.wiktionary.org/wiki/morph"]},{"word":"morph","phonetic":"/mɔː(ɹ)f/","phonetics":[{"text":"/mɔː(ɹ)f/","audio":"https://api.dictionaryapi.dev/media/pronunciations/en/morph-uk.mp3","sourceUrl":"https://commons.wikimedia.org/w/index.php?curid=88681167","license":{"name":"BY-SA 4.0","url":"https://creativecommons.org/licenses/by-sa/4.0"}}],"meanings":[{"partOfSpeech":"noun","definitions":[{"definition":"A computer-generated gradual change from one image to another.","synonyms":[],"antonyms":[]}],"synonyms":[],"antonyms":[]},{"partOfSpeech":"verb","definitions":[{"definition":"To change shape, from one form to another, through computer animation.","synonyms":[],"antonyms":[]},{"definition":"(of fantastic beings in science fiction or fantasy) To shapeshift.","synonyms":[],"antonyms":[]},{"definition":"To undergo dramatic change in a seamless and barely noticeable fashion.","synonyms":[],"antonyms":[]}],"synonyms":[],"antonyms":[]}],"license":{"name":"CC BY-SA 3.0","url":"https://creativecommons.org/licenses/by-sa/3.0"},"sourceUrls":["https://en.wiktionary.org/wiki/morph"]}]