[{"word":"puggy","phonetics":[{"audio":"https://api.dictionaryapi.dev/media/pronunciations/en/puggy-au.mp3","sourceUrl":"https://commons.wikimedia.org/w/index.php?curid=75649256","license":{"name":"BY-SA 4.0","url":"https://creativecommons.org/licenses/by-sa/4.0"}}],"meanings":[{"partOfSpeech":"adjective","definitions":[{"definition":"Resembling or characteristic of a pug dog.","synonyms":[],"antonyms":[],"example":"a puggy nose"},{"definition":"Sticky, claylike","synonyms":[],"antonyms":[]}],"synonyms":["claggy","tenacious"],"antonyms":[]}],"license":{"name":"CC BY-SA 3.0","url":"https://creativecommons.org/licenses/by-sa/3.0"},"sourceUrls":["https://en.wiktionary.org/wiki/puggy"]}]