[{"word":"rebid","phonetics":[],"meanings":[{"partOfSpeech":"noun","definitions":[{"definition":"A second or subsequent (normally higher) bid.","synonyms":[],"antonyms":[]}],"synonyms":[],"antonyms":[]},{"partOfSpeech":"verb","definitions":[{"definition":"To bid again on something.","synonyms":[],"antonyms":[]},{"definition":"To require a new set of bids for.","synonyms":[],"antonyms":[],"example":"We had to rebid the contract when accusations of fraud by other competitors occurred."},{"definition":"To bid a higher value of the current suit.","synonyms":[],"antonyms":[]}],"synonyms":[],"antonyms":[]}],"license":{"name":"CC BY-SA 3.0","url":"https://creativecommons.org/licenses/by-sa/3.0"},"sourceUrls":["https://en.wiktionary.org/wiki/rebid"]}]