[{"word":"rheme","phonetic":"/ɹiːm/","phonetics":[{"text":"/ɹiːm/","audio":""}],"meanings":[{"partOfSpeech":"noun","definitions":[{"definition":"The part of a sentence that provides new information regarding the current theme.","synonyms":[],"antonyms":[]},{"definition":"A sign that represents its object in respect of quality and so, in its signified interpretant, is represented as a character or mark; sumisign.","synonyms":[],"antonyms":[]}],"synonyms":[],"antonyms":[]}],"license":{"name":"CC BY-SA 3.0","url":"https://creativecommons.org/licenses/by-sa/3.0"},"sourceUrls":["https://en.wiktionary.org/wiki/rheme"]}]