[{"word":"taros","phonetics":[],"meanings":[{"partOfSpeech":"noun","definitions":[{"definition":"Colocasia esculenta, raised as a food primarily for its corm, which distantly resembles potato.","synonyms":["colocasia","elephant ears"],"antonyms":[]},{"definition":"Any of several other species with similar corms and growth habit in Colocasia, Alocasia etc.","synonyms":[],"antonyms":[]},{"definition":"Food from a taro plant.","synonyms":["dasheen"],"antonyms":[]}],"synonyms":["colocasia","elephant ears","dasheen"],"antonyms":[]}],"license":{"name":"CC BY-SA 3.0","url":"https://creativecommons.org/licenses/by-sa/3.0"},"sourceUrls":["https://en.wiktionary.org/wiki/taro","https://en.wiktionary.org/wiki/taros"]}]