[{"word":"vireo","phonetics":[],"meanings":[{"partOfSpeech":"noun","definitions":[{"definition":"Any of a number of small insectivorous passerine birds, of the genus Vireo, that have grey-green plumage.","synonyms":[],"antonyms":[]},{"definition":"Any bird of the family Vireonidae, which includes vireos, shrike-vireo, greenlets and peppershrikes.","synonyms":[],"antonyms":[]},{"definition":"(in plural) The family Vireonidae.","synonyms":[],"antonyms":[]}],"synonyms":[],"antonyms":[]}],"license":{"name":"CC BY-SA 3.0","url":"https://creativecommons.org/licenses/by-sa/3.0"},"sourceUrls":["https://en.wiktionary.org/wiki/vireo"]}]