[{"word":"cruet","phonetics":[],"meanings":[{"partOfSpeech":"noun","definitions":[{"definition":"A small bottle or container used to hold a condiment, such as salt, pepper, oil, or vinegar, for use at a dining table.","synonyms":[],"antonyms":[]},{"definition":"A stand for these containers.","synonyms":[],"antonyms":[]},{"definition":"A small vessel used to hold wine or water for the Eucharist.","synonyms":[],"antonyms":[]}],"synonyms":[],"antonyms":[]}],"license":{"name":"CC BY-SA 3.0","url":"https://creativecommons.org/licenses/by-sa/3.0"},"sourceUrls":["https://en.wiktionary.org/wiki/cruet"]}]