[{"word":"gnash","phonetic":"/næʃ/","phonetics":[{"text":"/næʃ/","audio":"https://api.dictionaryapi.dev/media/pronunciations/en/gnash-us.mp3","sourceUrl":"https://commons.wikimedia.org/w/index.php?curid=1772909","license":{"name":"BY-SA 3.0","url":"https://creativecommons.org/licenses/by-sa/3.0"}}],"meanings":[{"partOfSpeech":"noun","definitions":[{"definition":"A sudden snapping of the teeth.","synonyms":[],"antonyms":[]}],"synonyms":[],"antonyms":[]},{"partOfSpeech":"verb","definitions":[{"definition":"To grind (one's teeth) in pain or in anger.","synonyms":[],"antonyms":[],"example":"gnashing your teeth"},{"definition":"To grind between the teeth.","synonyms":[],"antonyms":[],"example":"The dog was gnashing a carpet"},{"definition":"To run away.","synonyms":[],"antonyms":[]}],"synonyms":[],"antonyms":[]}],"license":{"name":"CC BY-SA 3.0","url":"https://creativecommons.org/licenses/by-sa/3.0"},"sourceUrls":["https://en.wiktionary.org/wiki/gnash"]}]