[{"word":"ileus","phonetics":[],"meanings":[{"partOfSpeech":"noun","definitions":[{"definition":"(modern usage) Disruption of the normal propulsive ability of the gastrointestinal tract, due to failure of peristalsis.","synonyms":[],"antonyms":[]},{"definition":"(broad definition, now rare) Disruption of the normal propulsive ability of the gastrointestinal tract from any cause.","synonyms":[],"antonyms":[]}],"synonyms":[],"antonyms":[]}],"license":{"name":"CC BY-SA 3.0","url":"https://creativecommons.org/licenses/by-sa/3.0"},"sourceUrls":["https://en.wiktionary.org/wiki/ileus"]}]