{
  "word": "lease",
  "phonetic": "/liːs/",
  "phonetics": [
    {
      "text": "/liːs/",
      "audio": ""
    },
    {
      "text": "/liːs/",
      "audio": "https://api.dictionaryapi.dev/media/pronunciations/en/lease-us.mp3",
      "sourceUrl": "https://commons.wikimedia.org/w/index.php?curid=2651126",
      "license": {
        "name": "BY-SA 3.0",
        "url": "https://creativecommons.org/licenses/by-sa/3.0"
      }
    }
  ],
  "meanings": [
    {
      "partOfSpeech": "verb",
      "definitions": [
        {
          "definition": "(chiefly dialectal) To gather.",
          "synonyms": [],
          "antonyms": []
        },
        {
          "definition": "(chiefly dialectal) To pick, select, pick out; to pick up.",
          "synonyms": [],
          "antonyms": []
        },
        {
          "definition": "(chiefly dialectal) To glean.",
          "synonyms": [],
          "antonyms": []
        },
        {
          "definition": "(chiefly dialectal) To glean, gather up leavings.",
          "synonyms": [],
          "antonyms": []
        }
      ],
      "synonyms": [],
      "antonyms": []
    }
  ],
  "license": {
    "name": "CC BY-SA 3.0",
    "url": "https://creativecommons.org/licenses/by-sa/3.0"
  },
  "sourceUrls": [
    "https://en.wiktionary.org/wiki/lease"
  ]
}
