[{"word":"molts","phonetics":[],"meanings":[{"partOfSpeech":"noun","definitions":[{"definition":"The process of shedding or losing a covering of fur, feathers or skin etc.","synonyms":[],"antonyms":[],"example":"Some birds change colour during their winter moult."},{"definition":"The skin or feathers cast off during the process of moulting.","synonyms":["exuvia"],"antonyms":[]}],"synonyms":["exuvia"],"antonyms":[]},{"partOfSpeech":"verb","definitions":[{"definition":"To shed or lose a covering of hair or fur, feathers, skin, horns, etc, and replace it with a fresh one.","synonyms":["shed","slough"],"antonyms":[]},{"definition":"To shed in such a manner.","synonyms":[],"antonyms":[]}],"synonyms":["shed","slough"],"antonyms":[]}],"license":{"name":"CC BY-SA 3.0","url":"https://creativecommons.org/licenses/by-sa/3.0"},"sourceUrls":["https://en.wiktionary.org/wiki/molt","https://en.wiktionary.org/wiki/molts","https://en.wiktionary.org/wiki/moult"]}]