[{"word":"pinks","phonetics":[],"meanings":[{"partOfSpeech":"noun","definitions":[{"definition":"The common minnow, Phoxinus phoxinus.","synonyms":[],"antonyms":[]},{"definition":"A young Atlantic salmon, Salmo salar, before it becomes a smolt; a parr.","synonyms":[],"antonyms":[]}],"synonyms":[],"antonyms":[]},{"partOfSpeech":"noun","definitions":[{"definition":"A narrow boat.","synonyms":[],"antonyms":[]}],"synonyms":[],"antonyms":[]},{"partOfSpeech":"noun","definitions":[{"definition":"A stab.","synonyms":[],"antonyms":[]}],"synonyms":[],"antonyms":[]},{"partOfSpeech":"noun","definitions":[{"definition":"Any of various flowers in the genus Dianthus, sometimes called carnations.","synonyms":[],"antonyms":[],"example":"This garden in particular has a beautiful bed of pinks."},{"definition":"A perfect example; excellence, perfection; the embodiment of some quality.","synonyms":[],"antonyms":[],"example":"Your hat, madam, is the very pink of fashion."},{"definition":"The colour of this flower, between red and white; pale red.","synonyms":[],"antonyms":[],"example":"My new dress is a wonderful shade of pink."},{"definition":"Hunting pink; scarlet, as worn by hunters.","synonyms":[],"antonyms":[]},{"definition":"One of the colour balls used in snooker, with a value of 6 points.","synonyms":[],"antonyms":[],"example":"Oh dear, he's left himself snookered behind the pink."},{"definition":"An unlettered and uncultured, but relatively prosperous, member of the middle classes; compare Babbitt, bourgeoisie.","synonyms":[],"antonyms":[]},{"definition":"The vagina or vulva.","synonyms":[],"antonyms":[]}],"synonyms":[],"antonyms":[]},{"partOfSpeech":"noun","definitions":[{"definition":"A socialist who is not wholly communist.","synonyms":[],"antonyms":[]}],"synonyms":[],"antonyms":[]},{"partOfSpeech":"noun","definitions":[{"definition":"Flowers in the family Caryophyllaceae, sometimes called carnations.","synonyms":[],"antonyms":[]},{"definition":"The traditional scarlet jacket(s) worn by fox-hunters in the United Kingdom.","synonyms":[],"antonyms":[]}],"synonyms":[],"antonyms":[]}],"license":{"name":"CC BY-SA 3.0","url":"https://creativecommons.org/licenses/by-sa/3.0"},"sourceUrls":["https://en.wiktionary.org/wiki/pink","https://en.wiktionary.org/wiki/pinko","https://en.wiktionary.org/wiki/pinks"]}]