[{"word":"pucks","phonetic":"/pʌks/","phonetics":[{"text":"/pʌks/","audio":""}],"meanings":[{"partOfSpeech":"noun","definitions":[{"definition":"A mischievous or hostile spirit.","synonyms":[],"antonyms":[]}],"synonyms":["fairy","goblin"],"antonyms":[]},{"partOfSpeech":"noun","definitions":[{"definition":"A hard rubber disc; any other flat disc meant to be hit across a flat surface in a game.","synonyms":[],"antonyms":[]},{"definition":"An object shaped like a puck.","synonyms":[],"antonyms":[]},{"definition":"A pointing device with a crosshair.","synonyms":[],"antonyms":[]},{"definition":"(camogie) A penalty shot.","synonyms":[],"antonyms":[]}],"synonyms":[],"antonyms":[]},{"partOfSpeech":"noun","definitions":[{"definition":"(rural) billy goat","synonyms":[],"antonyms":[]}],"synonyms":[],"antonyms":[]}],"license":{"name":"CC BY-SA 3.0","url":"https://creativecommons.org/licenses/by-sa/3.0"},"sourceUrls":["https://en.wiktionary.org/wiki/puck","https://en.wiktionary.org/wiki/pucks"]}]