[{"word":"bidet","phonetic":"[ˈbiːdeɪ]","phonetics":[{"text":"[ˈbiːdeɪ]","audio":""},{"text":"[bɨˈdeɪ]","audio":"https://api.dictionaryapi.dev/media/pronunciations/en/bidet-us.mp3","sourceUrl":"https://commons.wikimedia.org/w/index.php?curid=36696490"}],"meanings":[{"partOfSpeech":"noun","definitions":[{"definition":"A low-mounted plumbing fixture or type of sink intended for washing the external genitalia and the anus.","synonyms":[],"antonyms":[]},{"definition":"A small horse formerly allowed to each trooper or dragoon for carrying his baggage.","synonyms":[],"antonyms":[]}],"synonyms":[],"antonyms":[]}],"license":{"name":"CC BY-SA 3.0","url":"https://creativecommons.org/licenses/by-sa/3.0"},"sourceUrls":["https://en.wiktionary.org/wiki/bidet"]}]