[{"word":"strop","phonetic":"/stɹɒp/","phonetics":[{"text":"/stɹɒp/","audio":"https://api.dictionaryapi.dev/media/pronunciations/en/strop-au.mp3","sourceUrl":"https://commons.wikimedia.org/w/index.php?curid=79241806","license":{"name":"BY-SA 4.0","url":"https://creativecommons.org/licenses/by-sa/4.0"}}],"meanings":[{"partOfSpeech":"noun","definitions":[{"definition":"A strap; more specifically a piece of leather or a substitute (notably canvas), or strip of wood covered with a suitable material, for honing a razor, in this sense also called razor strop.","synonyms":[],"antonyms":[]},{"definition":"A bad mood or temper (see stroppy.)","synonyms":[],"antonyms":[]},{"definition":"A piece of rope spliced into a circular wreath, and put round a block for hanging it.","synonyms":[],"antonyms":[]}],"synonyms":["huff"],"antonyms":[]},{"partOfSpeech":"verb","definitions":[{"definition":"To strap.","synonyms":[],"antonyms":[]},{"definition":"(recorded since 1842; now most used) To hone (a razor) with a strop.","synonyms":[],"antonyms":[],"example":"One should strop the razor before each shave."}],"synonyms":[],"antonyms":[]}],"license":{"name":"CC BY-SA 3.0","url":"https://creativecommons.org/licenses/by-sa/3.0"},"sourceUrls":["https://en.wiktionary.org/wiki/strop"]},{"word":"strop","phonetic":"/stɹɒp/","phonetics":[{"text":"/stɹɒp/","audio":"https://api.dictionaryapi.dev/media/pronunciations/en/strop-au.mp3","sourceUrl":"https://commons.wikimedia.org/w/index.php?curid=79241806","license":{"name":"BY-SA 4.0","url":"https://creativecommons.org/licenses/by-sa/4.0"}}],"meanings":[{"partOfSpeech":"verb","definitions":[{"definition":"To mark a sequence of letters syntactically as having a special property, such as being a keyword, e.g. by enclosing in apostrophes as in 'foo' or writing in uppercase as in FOO.","synonyms":[],"antonyms":[]}],"synonyms":[],"antonyms":[]}],"license":{"name":"CC BY-SA 3.0","url":"https://creativecommons.org/licenses/by-sa/3.0"},"sourceUrls":["https://en.wiktionary.org/wiki/strop"]},{"word":"strop","phonetic":"/stɹɒp/","phonetics":[{"text":"/stɹɒp/","audio":"https://api.dictionaryapi.dev/media/pronunciations/en/strop-au.mp3","sourceUrl":"https://commons.wikimedia.org/w/index.php?curid=79241806","license":{"name":"BY-SA 4.0","url":"https://creativecommons.org/licenses/by-sa/4.0"}}],"meanings":[{"partOfSpeech":"noun","definitions":[{"definition":"A poor-quality or unsaleable diamond.","synonyms":[],"antonyms":[]}],"synonyms":[],"antonyms":[]}],"license":{"name":"CC BY-SA 3.0","url":"https://creativecommons.org/licenses/by-sa/3.0"},"sourceUrls":["https://en.wiktionary.org/wiki/strop"]}]