{
  "word": "tongs",
  "phonetic": "/tɑŋz/",
  "phonetics": [
    {
      "text": "/tɑŋz/",
      "audio": ""
    },
    {
      "text": "/tɒŋz/",
      "audio": ""
    },
    {
      "text": "/tɔŋz/",
      "audio": "https://api.dictionaryapi.dev/media/pronunciations/en/tongs-us.mp3",
      "sourceUrl": "https://commons.wikimedia.org/w/index.php?curid=958927",
      "license": {
        "name": "BY-SA 3.0",
        "url": "https://creativecommons.org/licenses/by-sa/3.0"
      }
    }
  ],
  "meanings": [
    {
      "partOfSpeech": "noun",
      "definitions": [
        {
          "definition": "An instrument or tool used for picking things up without touching them with the hands or fingers, consisting of two slats or grips hinged at the end or in the middle, and sometimes including a spring to open the grips.",
          "synonyms": [],
          "antonyms": []
        },
        {
          "definition": "(by extension) A large scissors-like two-piece center-hinged forged-iron implement with oval-loop handles and with pointed tips turned inward (in the same plane as and perpendicular to the handles) to facilitate lifting and carrying a block of ice. Often called ice tongs.",
          "synonyms": [],
          "antonyms": []
        }
      ],
      "synonyms": [],
      "antonyms": []
    }
  ],
  "license": {
    "name": "CC BY-SA 3.0",
    "url": "https://creativecommons.org/licenses/by-sa/3.0"
  },
  "sourceUrls": [
    "https://en.wiktionary.org/wiki/tongs"
  ]
}
