[{"word":"woozy","phonetic":"/ˈwuːzi/","phonetics":[{"text":"/ˈwuːzi/","audio":"https://api.dictionaryapi.dev/media/pronunciations/en/woozy-us.mp3","sourceUrl":"https://commons.wikimedia.org/w/index.php?curid=951922","license":{"name":"BY-SA 3.0","url":"https://creativecommons.org/licenses/by-sa/3.0"}}],"meanings":[{"partOfSpeech":"adjective","definitions":[{"definition":"Queasy, dizzy, or disoriented","synonyms":[],"antonyms":[],"example":"I got off the rollercoaster feeling a bit woozy."},{"definition":"Intoxicated by drink or drugs","synonyms":[],"antonyms":[]}],"synonyms":["giddy","lightheaded","whifty"],"antonyms":[]}],"license":{"name":"CC BY-SA 3.0","url":"https://creativecommons.org/licenses/by-sa/3.0"},"sourceUrls":["https://en.wiktionary.org/wiki/woozy"]}]