[{"word":"campy","phonetic":"/ˈkæmpi/","phonetics":[{"text":"/ˈkæmpi/","audio":""}],"meanings":[{"partOfSpeech":"adjective","definitions":[{"definition":"Characterized by camp or kitsch, especially when deliberate or intentional.","synonyms":[],"antonyms":[],"example":"Stu liked to watch campy B-movie horror flicks from the 1950s, not because they scared him, but because he found them funny."}],"synonyms":["camp","corny","hammy","silly","tawdry","vulgar"],"antonyms":[]}],"license":{"name":"CC BY-SA 3.0","url":"https://creativecommons.org/licenses/by-sa/3.0"},"sourceUrls":["https://en.wiktionary.org/wiki/campy"]}]