[{"word":"croci","phonetics":[],"meanings":[{"partOfSpeech":"noun","definitions":[{"definition":"A perennial flowering plant (of the genus Crocus in the Iridaceae family). Saffron is obtained from the stamens of Crocus sativus.","synonyms":[],"antonyms":[]},{"definition":"Any of various similar flowering plants, such as the autumn crocus and prairie crocus.","synonyms":[],"antonyms":[]},{"definition":"A deep yellow powder, the oxide of some metal (especially iron), calcined to a red or deep yellow colour.","synonyms":[],"antonyms":[]},{"definition":"A fraudulent doctor; a quack.","synonyms":[],"antonyms":[]}],"synonyms":[],"antonyms":[]}],"license":{"name":"CC BY-SA 3.0","url":"https://creativecommons.org/licenses/by-sa/3.0"},"sourceUrls":["https://en.wiktionary.org/wiki/croci","https://en.wiktionary.org/wiki/crocus"]}]