[{"word":"houri","phonetic":"/ˈhʊəɹi/","phonetics":[{"text":"/ˈhʊəɹi/","audio":""}],"meanings":[{"partOfSpeech":"noun","definitions":[{"definition":"A nymph in the form of a beautiful virgin supposed to dwell in Paradise for the enjoyment of the faithful.","synonyms":[],"antonyms":[]},{"definition":"(by extension) Any voluptuous, beautiful woman.","synonyms":[],"antonyms":[]}],"synonyms":[],"antonyms":[]}],"license":{"name":"CC BY-SA 3.0","url":"https://creativecommons.org/licenses/by-sa/3.0"},"sourceUrls":["https://en.wiktionary.org/wiki/houri"]}]