[{"word":"oppos","phonetics":[],"meanings":[{"partOfSpeech":"noun","definitions":[{"definition":"A friend, associate or colleague.","synonyms":[],"antonyms":[]},{"definition":"Research into one's opponent's family, friends and past, which aims to uncover activities or interests which embarrass or discredit them (short for oppo research).","synonyms":[],"antonyms":[]}],"synonyms":[],"antonyms":[]}],"license":{"name":"CC BY-SA 3.0","url":"https://creativecommons.org/licenses/by-sa/3.0"},"sourceUrls":["https://en.wiktionary.org/wiki/oppo","https://en.wiktionary.org/wiki/oppos"]}]