[{"word":"outre","phonetics":[],"meanings":[{"partOfSpeech":"adjective","definitions":[{"definition":"Beyond what is customary or proper; extravagant.","synonyms":[],"antonyms":[]},{"definition":"Very unconventional.","synonyms":[],"antonyms":[]}],"synonyms":["bizarre","eccentric","outlandish"],"antonyms":[]}],"license":{"name":"CC BY-SA 3.0","url":"https://creativecommons.org/licenses/by-sa/3.0"},"sourceUrls":["https://en.wiktionary.org/wiki/outr%C3%A9","https://en.wiktionary.org/wiki/outre"]}]