[{"word":"riser","phonetic":"/ˈɹaɪ.zə(ɹ)/","phonetics":[{"text":"/ˈɹaɪ.zə(ɹ)/","audio":""},{"audio":"https://api.dictionaryapi.dev/media/pronunciations/en/riser-us.mp3","sourceUrl":"https://commons.wikimedia.org/w/index.php?curid=424822","license":{"name":"BY-SA 3.0","url":"https://creativecommons.org/licenses/by-sa/3.0"}}],"meanings":[{"partOfSpeech":"noun","definitions":[{"definition":"Someone or something which rises.","synonyms":[],"antonyms":[]},{"definition":"A platform or stand used to lift or elevate something.","synonyms":[],"antonyms":[],"example":"The choir stood on risers for the performance."},{"definition":"The vertical part of a step on a staircase.","synonyms":[],"antonyms":[]},{"definition":"The main body of a bow.","synonyms":[],"antonyms":[]},{"definition":"A vertical utility conduit, pipe or path between floors of a building for placement of cables (e.g. telephone, networking), or to convey fluids (e.g. gas, water).","synonyms":[],"antonyms":[]},{"definition":"A pipe connecting an individual exhaust port of an internal combustion engine to the muffler, particularly on aircraft.","synonyms":[],"antonyms":[]},{"definition":"A Manx cat with a showable short tail.","synonyms":[],"antonyms":[]},{"definition":"A strip of webbing joining a parachute's harness to the rigging lines.","synonyms":[],"antonyms":[]}],"synonyms":[],"antonyms":[]}],"license":{"name":"CC BY-SA 3.0","url":"https://creativecommons.org/licenses/by-sa/3.0"},"sourceUrls":["https://en.wiktionary.org/wiki/riser"]}]