[{"word":"scull","phonetic":"/skʌl/","phonetics":[{"text":"/skʌl/","audio":"https://api.dictionaryapi.dev/media/pronunciations/en/scull-au.mp3","sourceUrl":"https://commons.wikimedia.org/w/index.php?curid=75649643","license":{"name":"BY-SA 4.0","url":"https://creativecommons.org/licenses/by-sa/4.0"}}],"meanings":[{"partOfSpeech":"noun","definitions":[{"definition":"A single oar mounted at the stern of a boat and moved from side to side to propel the boat forward.","synonyms":[],"antonyms":[]},{"definition":"One of a pair of oars handled by a single rower.","synonyms":[],"antonyms":[]},{"definition":"A small rowing boat, for one person.","synonyms":[],"antonyms":[]},{"definition":"A light rowing boat used for racing by one, two, or four rowers, each operating two oars (sculls), one in each hand.","synonyms":[],"antonyms":[]}],"synonyms":[],"antonyms":[]},{"partOfSpeech":"verb","definitions":[{"definition":"To row a boat using a scull or sculls.","synonyms":[],"antonyms":[]},{"definition":"To skate while keeping both feet in contact with the ground or ice.","synonyms":[],"antonyms":[]}],"synonyms":[],"antonyms":[]}],"license":{"name":"CC BY-SA 3.0","url":"https://creativecommons.org/licenses/by-sa/3.0"},"sourceUrls":["https://en.wiktionary.org/wiki/scull"]},{"word":"scull","phonetic":"/skʌl/","phonetics":[{"text":"/skʌl/","audio":"https://api.dictionaryapi.dev/media/pronunciations/en/scull-au.mp3","sourceUrl":"https://commons.wikimedia.org/w/index.php?curid=75649643","license":{"name":"BY-SA 4.0","url":"https://creativecommons.org/licenses/by-sa/4.0"}}],"meanings":[{"partOfSpeech":"noun","definitions":[{"definition":"A skull cap. A small bowl-shaped helmet, without visor or bever.","synonyms":[],"antonyms":[]}],"synonyms":[],"antonyms":[]},{"partOfSpeech":"verb","definitions":[{"definition":"To drink the entire contents of (a drinking vessel) without pausing.","synonyms":[],"antonyms":[]}],"synonyms":["chug"],"antonyms":[]},{"partOfSpeech":"noun","definitions":[{"definition":"The main bones of the head considered as a unit; including the cranium, facial bones, and mandible.","synonyms":[],"antonyms":[]},{"definition":"A symbol for death; death's-head","synonyms":[],"antonyms":[]},{"definition":"The mind or brain.","synonyms":[],"antonyms":[]},{"definition":"A crust formed on the ladle, etc. by the partial cooling of molten metal.","synonyms":[],"antonyms":[]},{"definition":"The crown of the headpiece in armour.","synonyms":[],"antonyms":[]},{"definition":"A shallow bow-handled basket.","synonyms":[],"antonyms":[]}],"synonyms":["brainpan","harnpan"],"antonyms":[]}],"license":{"name":"CC BY-SA 3.0","url":"https://creativecommons.org/licenses/by-sa/3.0"},"sourceUrls":["https://en.wiktionary.org/wiki/scull","https://en.wiktionary.org/wiki/skull"]},{"word":"scull","phonetic":"/skʌl/","phonetics":[{"text":"/skʌl/","audio":"https://api.dictionaryapi.dev/media/pronunciations/en/scull-au.mp3","sourceUrl":"https://commons.wikimedia.org/w/index.php?curid=75649643","license":{"name":"BY-SA 4.0","url":"https://creativecommons.org/licenses/by-sa/4.0"}}],"meanings":[{"partOfSpeech":"noun","definitions":[{"definition":"A shoal of fish.","synonyms":[],"antonyms":[]}],"synonyms":[],"antonyms":[]}],"license":{"name":"CC BY-SA 3.0","url":"https://creativecommons.org/licenses/by-sa/3.0"},"sourceUrls":["https://en.wiktionary.org/wiki/scull"]},{"word":"scull","phonetic":"/skʌl/","phonetics":[{"text":"/skʌl/","audio":"https://api.dictionaryapi.dev/media/pronunciations/en/scull-au.mp3","sourceUrl":"https://commons.wikimedia.org/w/index.php?curid=75649643","license":{"name":"BY-SA 4.0","url":"https://creativecommons.org/licenses/by-sa/4.0"}}],"meanings":[{"partOfSpeech":"noun","definitions":[{"definition":"The skua gull.","synonyms":[],"antonyms":[]}],"synonyms":[],"antonyms":[]}],"license":{"name":"CC BY-SA 3.0","url":"https://creativecommons.org/licenses/by-sa/3.0"},"sourceUrls":["https://en.wiktionary.org/wiki/scull"]}]