[{"word":"skits","phonetics":[],"meanings":[{"partOfSpeech":"noun","definitions":[{"definition":"A short comic performance.","synonyms":[],"antonyms":[]},{"definition":"A jeer or sally; a brief satire.","synonyms":[],"antonyms":[]},{"definition":"A wanton girl; a wench.","synonyms":[],"antonyms":[]}],"synonyms":[],"antonyms":[]}],"license":{"name":"CC BY-SA 3.0","url":"https://creativecommons.org/licenses/by-sa/3.0"},"sourceUrls":["https://en.wiktionary.org/wiki/skit","https://en.wiktionary.org/wiki/skits"]}]